osbot_aws/AWS_Config.py
osbot_aws/OSBot_Setup.py
osbot_aws/__init__.py
osbot_aws/apis/ACM.py
osbot_aws/apis/API_Gateway.py
osbot_aws/apis/Athena.py
osbot_aws/apis/Boto_Helpers.py
osbot_aws/apis/Cloud_Trail.py
osbot_aws/apis/Cloud_Watch.py
osbot_aws/apis/Cloud_Watch_Logs.py
osbot_aws/apis/CodeBuild.py
osbot_aws/apis/Cognito_IDP.py
osbot_aws/apis/ECR.py
osbot_aws/apis/Events.py
osbot_aws/apis/Firehose.py
osbot_aws/apis/Kinesis.py
osbot_aws/apis/Logs.py
osbot_aws/apis/SQS.py
osbot_aws/apis/SSM.py
osbot_aws/apis/Secrets.py
osbot_aws/apis/Session.py
osbot_aws/apis/__init__.py
osbot_aws/apis/shell/Http__Remote_Shell.py
osbot_aws/apis/shell/Lambda_Shell.py
osbot_aws/apis/shell/Shell_Client.py
osbot_aws/apis/shell/Shell_Client__Local_Docker.py
osbot_aws/apis/shell/Shell_Server.py
osbot_aws/apis/shell/__init__.py
osbot_aws/apis/test_helpers/Temp_Aws_Roles.py
osbot_aws/apis/test_helpers/Temp_EC2_Instance.py
osbot_aws/apis/test_helpers/Temp_Event_Rule.py
osbot_aws/apis/test_helpers/Temp_Event_Rule_To_SQS_Queue.py
osbot_aws/apis/test_helpers/Temp_Folder_With_Lambda_File.py
osbot_aws/apis/test_helpers/Temp_IAM_Role.py
osbot_aws/apis/test_helpers/Temp_IAM_User.py
osbot_aws/apis/test_helpers/Temp_Lambda.py
osbot_aws/apis/test_helpers/Temp_S3_Zip_With_Lambda_File.py
osbot_aws/apis/test_helpers/Temp_SQS_Queue.py
osbot_aws/apis/test_helpers/Temp_VPC.py
osbot_aws/apis/test_helpers/__init__.py
osbot_aws/aws/__init__.py
osbot_aws/aws/apigateway/API_Gateway_Management_API.py
osbot_aws/aws/apigateway/API_Gateway_V2.py
osbot_aws/aws/apigateway/API_Gateway_V2__with_temp_role.py
osbot_aws/aws/apigateway/__init__.py
osbot_aws/aws/apigateway/apigw_dydb/WS__Connection.py
osbot_aws/aws/apigateway/apigw_dydb/WS__DyDB.py
osbot_aws/aws/apigateway/apigw_dydb/WS__Handle_Events.py
osbot_aws/aws/apigateway/apigw_dydb/WS__Handle_Lambda.py
osbot_aws/aws/apigateway/apigw_dydb/__init__.py
osbot_aws/aws/apigateway/lambdas/Deploy__lambda_web_sockets.py
osbot_aws/aws/apigateway/lambdas/__init__.py
osbot_aws-2.39.10.dist-info/LICENSE
osbot_aws-2.39.10.dist-info/METADATA
osbot_aws-2.39.10.dist-info/WHEEL
osbot_aws-2.39.10.dist-info/RECORD
