Metadata-Version: 2.1
Name: osbot_aws
Version: 2.39.10
Summary: OWASP Security Bot - AWS
Home-page: https://github.com/owasp-sbot/OSBot-AWS
License: MIT
Author: Dinis Cruz
Author-email: dinis.cruz@owasp.org
Requires-Python: >=3.9,<4.0
Classifier: License :: OSI Approved :: MIT License
Classifier: Programming Language :: Python :: 3
Classifier: Programming Language :: Python :: 3.9
Classifier: Programming Language :: Python :: 3.10
Classifier: Programming Language :: Python :: 3.11
Classifier: Programming Language :: Python :: 3.12
Requires-Dist: boto3
Requires-Dist: osbot-utils
Project-URL: Repository, https://github.com/owasp-sbot/OSBot-AWS
